nodeshot_citysdk_synchronizers/__init__.py
nodeshot_citysdk_synchronizers/citysdk_mobility.py
nodeshot_citysdk_synchronizers/citysdk_tourism.py
nodeshot_citysdk_synchronizers/geojson_citysdk_mobility.py
nodeshot_citysdk_synchronizers/geojson_citysdk_tourism.py
nodeshot_citysdk_synchronizers/openwisp_citysdk_tourism.py
nodeshot_citysdk_synchronizers/provincerometraffic.py
nodeshot_citysdk_synchronizers/provinciawifi.py
nodeshot_citysdk_synchronizers/provinciawifi_citysdk_mobility.py
nodeshot_citysdk_synchronizers/provinciawifi_citysdk_tourism.py
nodeshot_citysdk_synchronizers/settings.py
nodeshot_citysdk_synchronizers/tests.py
nodeshot_citysdk_synchronizers-0.3.1.dist-info/DESCRIPTION.rst
nodeshot_citysdk_synchronizers-0.3.1.dist-info/METADATA
nodeshot_citysdk_synchronizers-0.3.1.dist-info/RECORD
nodeshot_citysdk_synchronizers-0.3.1.dist-info/WHEEL
nodeshot_citysdk_synchronizers-0.3.1.dist-info/metadata.json
nodeshot_citysdk_synchronizers-0.3.1.dist-info/top_level.txt
