Metadata-Version: 2.0
Name: nodeshot-citysdk-synchronizers
Version: 0.3.1
Summary: Additional synchronizers for nodeshot.interop.sync
Home-page: http://github.com/nemesisdesign/nodeshot-citysdk-synchronizers/
Author: Federico Capoano
Author-email: f[dot]capoano[at]cineca[dot]it
License: BSD
Platform: UNKNOWN
Requires-Dist: nodeshot
